curator
setup.cfg
setup.py
Agora_Curator.egg-info/PKG-INFO
Agora_Curator.egg-info/SOURCES.txt
Agora_Curator.egg-info/dependency_links.txt
Agora_Curator.egg-info/namespace_packages.txt
Agora_Curator.egg-info/requires.txt
Agora_Curator.egg-info/top_level.txt
agora/__init__.py
agora/curator/__init__.py
agora/curator/metadata.json
agora/curator/actions/__init__.py
agora/curator/actions/enrichment.py
agora/curator/daemons/__init__.py
agora/curator/daemons/fragment.py
agora/curator/server/__init__.py
agora/curator/server/config.py