Metadata-Version: 1.1
Name: Agora-Curator
Version: 0.1.2
Summary: A service responsible for enriching resources that belong to a Linked Data Platform powered by Agora
Home-page: https://github.com/smartdeveloperhub/agora-stoa.git
Author: Fernando Serena
Author-email: fernando.serena@centeropenmiddleware.com
License: Apache 2
Download-URL: https://github.com/smartdeveloperhub/agora-curator/tarball/0.1.2
Keywords: linked-data,ontology,fragments
Platform: UNKNOWN
